./.gitignore
./.python-version
./Dockerfile
./LICENSE
./PKG-INFO
./README.md
./glama.json
./main.py
./pyproject.toml
./smithery.yaml
./uv.lock
iflow_mcp_cleanuri_url_shorterner-0.1.1.dist-info/METADATA
iflow_mcp_cleanuri_url_shorterner-0.1.1.dist-info/WHEEL
iflow_mcp_cleanuri_url_shorterner-0.1.1.dist-info/entry_points.txt
iflow_mcp_cleanuri_url_shorterner-0.1.1.dist-info/licenses/LICENSE
iflow_mcp_cleanuri_url_shorterner-0.1.1.dist-info/RECORD
