Metadata-Version: 2.4
Name: iflow-mcp-cleanuri-url-shorterner
Version: 0.1.1
Summary: A URL shortener MCP server using CleanURI API
Author-email: Talismanic <your.email@example.com>
License-File: LICENSE
Requires-Python: >=3.10
Requires-Dist: httpx>=0.28.1
Requires-Dist: mcp[cli]>=1.3.0
